cli/__init__.py
cli/compare.py
cli/stats.py
libs/__init__.py
libs/mlvideos.py
src/Comparator.py
src/Pcap.py
src/__init__.py
pcapstats-0.0.1.dist-info/LICENSE.md
pcapstats-0.0.1.dist-info/METADATA
pcapstats-0.0.1.dist-info/WHEEL
pcapstats-0.0.1.dist-info/entry_points.txt
pcapstats-0.0.1.dist-info/top_level.txt
pcapstats-0.0.1.dist-info/RECORD
